runhelper/__init__.py
runhelper/log.py
runhelper/run.py
runhelper-0.2.4.dist-info/METADATA
runhelper-0.2.4.dist-info/WHEEL
runhelper-0.2.4.dist-info/licenses/LICENSE
runhelper-0.2.4.dist-info/RECORD
