Metadata-Version: 2.3
Name: runhelper
Version: 0.2.4
Summary: A small library to help running and logging the behaviour of research tools
Project-URL: repository, https://github.com/RicardoBrancas/runhelper
Author-email: Ricardo Brancas <ricardo.brancas@tecnico.ulisboa.pt>
License:                     GNU GENERAL PUBLIC LICENSE
License-File: LICENSE
Requires-Python: >=3.10
Requires-Dist: ordered-set
Requires-Dist: tqdm
